betterweb/__init__.py
betterweb/shared.py
betterweb/types.py
betterweb/client/__init__.py
betterweb/client/console/__init__.py
betterweb/client/localstorage/__init__.py
betterweb/client/router/__init__.py
betterweb/js/tsconfig.json
betterweb/js/src/conection.ts
betterweb/server/__init__.py
betterweb/server/app.py
betterweb/server/default.html
betterweb/server/dom.py
betterweb/server/router.py
betterweb/server/api/__init__.py
betterweb/server/api/request.py
betterweb/server/api/route.py
betterweb/server/api/state.py
betterweb/server/api/types.py
betterweb/server/api/response/__init__.py
betterweb/server/api/response/constructor.py
betterweb/server/api/response/error.py
betterweb/server/api/response/response.py
betterweb/server/api/response/stream.py
betterweb/server/api/response/utils/__init__.py
betterweb/server/api/response/utils/cookie.py
betterweb/server/api/response/utils/headers.py
betterweb/server/api/response/utils/url.py
betterweb/server/predefined/errors.py
betterweb/server/predefined/ws.py
betterweb-0.1.3.dist-info/METADATA
betterweb-0.1.3.dist-info/WHEEL
betterweb-0.1.3.dist-info/entry_points.txt
betterweb-0.1.3.dist-info/RECORD
