Metadata-Version: 2.4
Name: betterweb
Version: 0.1.3
Summary: A simple web framework for Python.
Author-email: R5dan <r5dan@outlook.com>
Requires-Python: >=3.13
Requires-Dist: datetime>=5.5
Requires-Dist: msgspec>=0.19.0
Requires-Dist: uvicorn[standard]>=0.35.0
